Metadata-Version: 1.0
Name: fink
Version: 0.0.1
Summary: Fink UI
Home-page: UNKNOWN
Author: Bülent Aldemir
Author-email: buelent@e-evolution.de
License: MIT
Platform: UNKNOWN
